cluster_helper/__init__.py
cluster_helper/cluster.py
cluster_helper/lsf.py
cluster_helper/slurm.py
cluster_helper/utils.py
cluster_helper/log/__init__.py
ipython_cluster_helper-0.6.2.dist-info/METADATA
ipython_cluster_helper-0.6.2.dist-info/RECORD
ipython_cluster_helper-0.6.2.dist-info/WHEEL
ipython_cluster_helper-0.6.2.dist-info/top_level.txt
