Metadata-Version: 2.1
Name: ipython-cluster-helper
Version: 0.6.2
Summary: Simplify IPython cluster start up and use for multiple schedulers.
Home-page: https://github.com/roryk/ipython-cluster-helper
Author: Rory Kirchner
Author-email: rory.kirchner@gmail.com
License: MIT
Platform: UNKNOWN
Requires-Dist: setuptools (>=18.5)
Requires-Dist: pyzmq (>=2.1.11)
Requires-Dist: ipython (<6.0.0)
Requires-Dist: ipyparallel (>=6.0.2)
Requires-Dist: netifaces (>=0.10.3)
Requires-Dist: six (>=1.10.0)
